processing/__init__.py
processing/combination.py
processing/transformation.py
image_processing_rafael_rodrigo-0.0.2.dist-info/METADATA
image_processing_rafael_rodrigo-0.0.2.dist-info/WHEEL
image_processing_rafael_rodrigo-0.0.2.dist-info/top_level.txt
image_processing_rafael_rodrigo-0.0.2.dist-info/RECORD
