Metadata-Version: 2.1
Name: image_processing_rafael_rodrigo
Version: 0.0.2
Summary: Package image processing
Home-page: https://github.com/raf-rodrigo/python-pacote-image-processing.git
Author: Rafael Rodrigo
Requires-Python: >=3.4
